README.md
setup.py
magicset/__init__.py
magicset/__version__.py
magicset/idcard.py
magicset/imageedit.py
magicset.egg-info/PKG-INFO
magicset.egg-info/SOURCES.txt
magicset.egg-info/dependency_links.txt
magicset.egg-info/top_level.txt
magicset.egg-info/zip-safe