Metadata-Version: 2.1
Name: magicset
Version: 1.0.0
Summary: magicset
Home-page: https://pypi.org/project/magicset/#description
Author: goblinintree
Author-email: goblinintree@126.com
License: MIT
Keywords: magicset,test
Platform: all
Classifier: Environment :: Web Environment
Classifier: License :: OSI Approved :: MIT License
Classifier: Operating System :: Microsoft
Classifier: Programming Language :: Python :: 3.7
